AUTHORS
ChangeLog
LICENSE
README.md
frontend.py
requirements.txt
setup.cfg
setup.py
lyricscraper/__init__.py
lyricscraper/lyrics.py
lyricscraper.egg-info/PKG-INFO
lyricscraper.egg-info/SOURCES.txt
lyricscraper.egg-info/dependency_links.txt
lyricscraper.egg-info/not-zip-safe
lyricscraper.egg-info/pbr.json
lyricscraper.egg-info/requires.txt
lyricscraper.egg-info/top_level.txt
lyricscraper/engines/azlyrics.py
lyricscraper/engines/base.py
lyricscraper/engines/metro_lyrics.py
lyricscraper/engines/pylyrics.py
tests/__init__.py
tests/engine_test.py
tests/lyrics_test.py