Metadata-Version: 1.0
Name: lyricscraper
Version: 1.0.0
Summary: Hunt down lyrics using multiple backends.
Home-page: https://github.com/chrisnorman7/
Author: Chris Norman
Author-email: chris.norman2@googlemail.com
License: MPL-2
Platform: UNKNOWN
